oarepo_model_builder_polymorphic/__init__.py
oarepo_model_builder_polymorphic/datatypes/__init__.py
oarepo_model_builder_polymorphic/datatypes/polymorphic.py
oarepo_model_builder_polymorphic-1.0.2.dist-info/METADATA
oarepo_model_builder_polymorphic-1.0.2.dist-info/WHEEL
oarepo_model_builder_polymorphic-1.0.2.dist-info/entry_points.txt
oarepo_model_builder_polymorphic-1.0.2.dist-info/top_level.txt
oarepo_model_builder_polymorphic-1.0.2.dist-info/RECORD
