Metadata-Version: 2.1
Name: oarepo-model-builder-polymorphic
Version: 1.0.2
Summary: Model builder plugin for oarepo-polymorphic
Requires-Dist: langcodes >=3.3.0
Requires-Dist: oarepo-model-builder >=4.0.0
Provides-Extra: tests
Requires-Dist: pytest >=7 ; extra == 'tests'
